callableExpressionParser.py
callableExpressionParser-1.0.2.dist-info/LICENSE
callableExpressionParser-1.0.2.dist-info/METADATA
callableExpressionParser-1.0.2.dist-info/WHEEL
callableExpressionParser-1.0.2.dist-info/top_level.txt
callableExpressionParser-1.0.2.dist-info/RECORD
