Metadata-Version: 2.1
Name: callableExpressionParser
Version: 1.0.2
Summary: Math Expression Parser that works with [ + - * / ^ // ! ] operators, constants [ pi ], functions [ exp, log, ln ], strings ["testString"], and [variables] out of the box and can be expanded to cover more use cases!
Author: Michael Stolte
Author-email: Michael Stolte <michael@stolte.us>
License: MIT License        
Project-URL: Homepage, https://github.com/mastoltejr/expressionParser
Keywords: expression,math,parser,equation
Classifier: License :: OSI Approved :: MIT License
Classifier: Programming Language :: Python
Classifier: Programming Language :: Python :: 3
Requires-Python: >=3.8.0
License-File: LICENSE
Requires-Dist: python-dateutil (>=2.8.2)
Provides-Extra: dev
